<?xml version="1.0" encoding="UTF-8"?>
<objects serializationModel="Studio.02.01.00">
	<object class="Workspace" id="{df8489f7-9903-4013-909f-cc1ed9ac459f}">
		<relationship name="masterEventFolder">
			<destination>{c39e3537-e758-4eb7-a0e9-bf5aa69590e3}</destination>
		</relationship>
		<relationship name="masterTagFolder">
			<destination>{36e00baa-ce9d-40d7-a8f9-60c5380cb442}</destination>
		</relationship>
		<relationship name="masterEffectPresetFolder">
			<destination>{761c8c1b-bc27-4139-b2d2-f7d9fb320225}</destination>
		</relationship>
		<relationship name="masterParameterPresetFolder">
			<destination>{114a3c38-eb2f-488c-ac55-841d17186e6a}</destination>
		</relationship>
		<relationship name="masterBankFolder">
			<destination>{712d16a7-7faf-4e8a-95eb-b804f5230870}</destination>
		</relationship>
		<relationship name="masterSandboxFolder">
			<destination>{851cf77e-f461-4a88-bba0-8afbfb5491bc}</destination>
		</relationship>
		<relationship name="masterAssetFolder">
			<destination>{68eec434-8c1a-49a5-b03b-4dd76b969c6f}</destination>
		</relationship>
		<relationship name="mixer">
			<destination>{7465c968-b037-455f-8a96-c89479912c77}</destination>
		</relationship>
		<relationship name="profilerSessionFolder">
			<destination>{3f268a70-1598-41b8-a3cc-123ab1cbeb93}</destination>
		</relationship>
		<relationship name="platforms">
			<destination>{278278b4-54b8-4809-ba0d-a995f0330734}</destination>
		</relationship>
	</object>
</objects>
